MANIFEST.in
README.md
README.rst
setup.py
django_multilingualfield.egg-info/PKG-INFO
django_multilingualfield.egg-info/SOURCES.txt
django_multilingualfield.egg-info/dependency_links.txt
django_multilingualfield.egg-info/not-zip-safe
django_multilingualfield.egg-info/requires.txt
django_multilingualfield.egg-info/top_level.txt
multilingualfield/__init__.py
multilingualfield/admin.py
multilingualfield/datastructures.py
multilingualfield/fields.py
multilingualfield/forms.py
multilingualfield/models.py
multilingualfield/utils.py
multilingualfield/widgets.py
multilingualfield/static/multilingualfield/css/multilingualfield-djangoadmin.css
multilingualfield/templatetags/__init__.py
multilingualfield/templatetags/multilingual_tags.py