Metadata-Version: 1.1
Name: django-multilingualfield
Version: 0.3.1
Summary: A south-compatible suite of django fields that make it easy to manage multiple translations of text-based content (including files/images).
Home-page: http://github.com/WGBH/django-multilingualfield/
Author: Jonathan Ellenberger
Author-email: jonathan_ellenberger@wgbh.org
License: MIT License, see LICENSE
Platform: UNKNOWN
Classifier: Framework :: Django
